{
    "Version": "2012-10-17",
    "Statement": [
        {
            "Effect": "Allow",
            "Action": [
                "acm:DescribeCertificate",
                "acm:ListCertificates",
                "acm:GetCertificate",
                "ec2:AuthorizeSecurityGroupIngress",
                "ec2:CreateSecurityGroup",
                "ec2:CreateTags",
                "ec2:DeleteTags",
                "ec2:DeleteSecurityGroup",
                "ec2:DescribeAccountAttributes",
                "ec2:DescribeAddresses",
                "ec2:DescribeInstances",
                "ec2:DescribeInternetGateways",
                "ec2:DescribeNetworkInterfaces",
                "ec2:DescribeSecurityGroups",
                "ec2:DescribeSubnets",
                "ec2:DescribeTags",
                "ec2:DescribeVpcs",
                "ec2:ModifyInstanceAttribute",
                "ec2:ModifyNetworkInterfaceAttribute",
                "ec2:RevokeSecurityGroupIngress",
                "elasticloadbalancing:AddListenerCertificates",
                "elasticloadbalancing:AddTags",
                "elasticloadbalancing:CreateListener",
                "elasticloadbalancing:CreateLoadBalancer",
                "elasticloadbalancing:CreateRule",
                "elasticloadbalancing:CreateTargetGroup",
                "elasticloadbalancing:DeleteListener",
                "elasticloadbalancing:DeleteLoadBalancer",
                "elasticloadbalancing:DeleteRule",
                "elasticloadbalancing:DeleteTargetGroup",
                "elasticloadbalancing:DeregisterTargets",
                "elasticloadbalancing:DescribeListenerCertificates",
                "elasticloadbalancing:DescribeListeners",
                "elasticloadbalancing:DescribeLoadBalancers",
                "elasticloadbalancing:DescribeLoadBalancerAttributes",
                "elasticloadbalancing:DescribeRules",
                "elasticloadbalancing:DescribeSSLPolicies",
                "elasticloadbalancing:DescribeTags",
                "elasticloadbalancing:DescribeTargetGroups",
                "elasticloadbalancing:DescribeTargetGroupAttributes",
                "elasticloadbalancing:DescribeTargetHealth",
                "elasticloadbalancing:ModifyListener",
                "elasticloadbalancing:ModifyLoadBalancerAttributes",
                "elasticloadbalancing:ModifyRule",
                "elasticloadbalancing:ModifyTargetGroup",
                "elasticloadbalancing:ModifyTargetGroupAttributes",
                "elasticloadbalancing:RegisterTargets",
                "elasticloadbalancing:RemoveListenerCertificates",
                "elasticloadbalancing:RemoveTags",
                "elasticloadbalancing:SetIpAddressType",
                "elasticloadbalancing:SetSecurityGroups",
                "elasticloadbalancing:SetSubnets",
                "elasticloadbalancing:SetWebAcl",
                "iam:CreateServiceLinkedRole",
                "iam:GetServerCertificate",
                "iam:ListServerCertificates",
                "wafv2:GetWebACL",
                "wafv2:GetWebACLForResource",
                "wafv2:AssociateWebACL",
                "wafv2:DisassociateWebACL",
                "shield:DescribeProtection",
                "shield:CreateProtection",
                "shield:DeleteProtection",
                "shield:DescribeSubscription",
                "shield:ListProtections"
            ],
            "Resource": "*"
        }
    ]
}
eksctl create iamserviceaccount \
  --cluster tmp-cluster \
  --namespace kube-system \
  --name aws-load-balancer-controller1 \
  --attach-policy-arn arn:aws:iam::767397701943:policy/AWSLoadBalancerControllerIAMPolicy1 \
  --approve

  helm install aws-load-balancer-controller eks/aws-load-balancer-controller \
  -n kube-system \
  --set clusterName=tmp-cluster \
  --set serviceAccount.create=false \
  --set serviceAccount.name=aws-load-balancer-controllercurl -O https://raw.githubusercontent.com/kubernetes-sigs/aws-load-balancer-controller/v2.7.2/docs/install/iam_policy.json
  